{
  "github": {
    "id": 8245,
    "name": "Antonio Salazar Cardozo",
    "company": "@thesis, @tallyhowallet, @keep-network",
    "blog": "https://keybase.io/shadowfiend",
    "location": "Atlanta, GA",
    "email": "savedfastcool@gmail.com",
    "bio": "Half Colombian, half Greek, half crazy. CTO at @thesis, contributor to @keep-network, @tahowallet. ",
    "twitterUsername": null,
    "publicRepos": 91,
    "publicGists": 29,
    "followers": 141,
    "following": 3,
    "createdAt": "2008-04-23T05:15:45Z"
  }
}